<?xml version="1.0" encoding="utf-8" ?>
<!-- Copyright 2023 - TODAY, Marcel Savegnago <marcel.savegnago@escodoo.com.br>
     License AGPL-3.0 or later (https://www.gnu.org/licenses/agpl). -->
<odoo>

    <record id="survey_view_form" model="ir.ui.view">
        <field name="name">survey.survey.view.form</field>
        <field name="model">survey.survey</field>
        <field name="inherit_id" ref="survey.survey_form" />
        <field name="arch" type="xml">
            <field name="access_mode" position="after">
                <field name="is_fsm_order_survey" />
            </field>
        </field>
    </record>

</odoo>
