<odoo>
    <!-- Worker states -->
    <record id="worker_stage_1" model="fsm.stage">
        <field name="name">Draft</field>
        <field name="sequence">1</field>
        <field name="stage_type">worker</field>
    </record>
    <record id="worker_stage_2" model="fsm.stage">
        <field name="name">Active</field>
        <field name="sequence">2</field>
        <field name="stage_type">worker</field>
    </record>
    <record id="worker_stage_3" model="fsm.stage">
        <field name="name">Inactive</field>
        <field name="sequence">3</field>
        <field name="stage_type">worker</field>
    </record>
    <!-- persons -->
    <record id="person_1" model="fsm.person">
        <field name="name">Alice</field>
    </record>
    <record id="person_2" model="fsm.person">
        <field name="name">Brett</field>
    </record>
    <record id="person_3" model="fsm.person">
        <field name="name">Chris</field>
    </record>
</odoo>
